zs2decode/__init__.py
zs2decode/encoder.py
zs2decode/parser.py
zs2decode/util.py
zs2decode-0.3.3.dist-info/licenses/LICENSE
zs2decode-0.3.3.dist-info/METADATA
zs2decode-0.3.3.dist-info/WHEEL
zs2decode-0.3.3.dist-info/top_level.txt
zs2decode-0.3.3.dist-info/RECORD
